blankit/__init__.py
blankit/py.typed
blankit/scanner.py
blankit/utils.py
blankit-0.2.1.dist-info/METADATA
blankit-0.2.1.dist-info/WHEEL
blankit-0.2.1.dist-info/RECORD
