Metadata-Version: 2.4
Name: blankit
Version: 0.2.1
Summary: Detection and redaction of PII using GLiNER
Author-email: Alex Lee <ajlee3141@gmail.com>
Requires-Python: >=3.10
Requires-Dist: black>=24.8.0
Requires-Dist: gliner>=0.2.19
Requires-Dist: pandas>=2.0.3
Requires-Dist: pytest>=8.3.5
Requires-Dist: ruff>=0.11.9
